py_sample
