Metadata-Version: 1.0
Name: hellotest989
Version: 1.1.2
Summary: Sample package for Gemfury
Home-page: http://www.gemfury.com
Author: Michael Rykov
Author-email: michael@gemfury.com
License: UNKNOWN
Platform: UNKNOWN
